MANIFEST.in
README.rst
setup.py
pyvertica/__init__.py
pyvertica/batch.py
pyvertica/connection.py
pyvertica/importer.py
pyvertica/migrate.py
pyvertica.egg-info/PKG-INFO
pyvertica.egg-info/SOURCES.txt
pyvertica.egg-info/dependency_links.txt
pyvertica.egg-info/requires.txt
pyvertica.egg-info/top_level.txt
pyvertica/tests/__init__.py
pyvertica/tests/unit/__init__.py
pyvertica/tests/unit/test_batch.py
pyvertica/tests/unit/test_connection.py
pyvertica/tests/unit/test_importer.py
pyvertica/tests/unit/test_migrator.py
scripts/vertica_batch_import
scripts/vertica_migrate