Metadata-Version: 1.0
Name: pyvertica
Version: 1.6.1
Summary: Tools for performing batch imports into Vertica
Home-page: https://github.com/spilgames/pyvertica
Author: Guillaume Roger, Orne Brocaar
Author-email: datawarehouse@spilgames.com
License: BSD
Platform: UNKNOWN
